{"name":"한국대학교육협의회_대학알리미 재정 현황","description":"등록금 현황, 장학금 수혜 현황, 학자금 대출 학생 수, 학생1인당 교육(투자)비 등","url":"https://www.data.go.kr/data/15038392/openapi.do","keywords":"대학알리미,대학정보공시,재정","license":"이용허락범위 제한 없음","dateCreated":"2019-11-11","dateModified":"2021-11-23","datePublished":"2019-11-11","creator":{"name":"한국대학교육협의회","contactPoint":{"contactType":"대학정보공시센터","telephone":"02-6919-3891","@type":"ContactPoint"},"@type":"Organization"},"additionalType":"교육 - 고등교육","datasetTimeInterval":"실시간","encodingFormat":"XML","@context":"https://schema.org","@type":"Dataset"}